tw_hooks/__init__.py
tw_hooks/base_hooks/__init__.py
tw_hooks/base_hooks/base_hook.py
tw_hooks/base_hooks/on_add_hook.py
tw_hooks/base_hooks/on_exit_hook.py
tw_hooks/base_hooks/on_launch_hook.py
tw_hooks/base_hooks/on_modify_hook.py
tw_hooks/hooks/__init__.py
tw_hooks/hooks/auto_tag_based_on_tags.py
tw_hooks/hooks/correct_tag_names.py
tw_hooks/hooks/detect_mutually_exclusive_tags.py
tw_hooks/hooks/post_latest_start_to_i3_status.py
tw_hooks/hooks/warn_on_task_congestion.py
tw_hooks/py.typed
tw_hooks/scripts/install_hook_shims.py
tw_hooks/types.py
tw_hooks/utils.py
tw_hooks-0.1.6.dist-info/entry_points.txt
tw_hooks-0.1.6.dist-info/LICENSE.md
tw_hooks-0.1.6.dist-info/WHEEL
tw_hooks-0.1.6.dist-info/METADATA
tw_hooks-0.1.6.dist-info/RECORD
