Metadata-Version: 2.1
Name: tw-hooks
Version: 0.1.6
Summary: Collection of Taskwarrior hooks
Home-page: https://github.com/bergercookie/tw-hooks
License: MIT
Author: Nikos Koukis
Author-email: nickkouk@gmail.com
Requires-Python: >=3.8,<4.0
Classifier: Framework :: Pytest
Classifier: License :: OSI Approved :: MIT License
Classifier: Natural Language :: English
Classifier: Operating System :: Unix
Classifier: Programming Language :: Python
Classifier: Programming Language :: Python :: 3
Classifier: Programming Language :: Python :: 3.8
Classifier: Programming Language :: Python :: 3.9
Classifier: Programming Language :: Python :: 3.10
Classifier: Programming Language :: Python :: 3 :: Only
Classifier: Programming Language :: Python :: 3.10
Classifier: Programming Language :: Python :: 3.8
Classifier: Programming Language :: Python :: 3.9
Classifier: Topic :: Utilities
Requires-Dist: bubop (==0.1.8)
Project-URL: Repository, https://github.com/bergercookie/tw-hooks
